face_test/__init__.py
face_test/bbox_anchor.py
face_test/eval_widerface.py
face_test/get_config.py
face_test/get_widerface_txt.py
face_test/onnx2trt.py
face_test/print_info.py
face_test/data/__init__.py
face_test/data/constant.py
face_test/data/image.py
face_test/data/experiments/__init__.py
face_test/data/experiments/AFLW/__init__.py
face_test/data/experiments/AFLW/pip_32_16_60_r18_l2_l1_10_1_nb10.py
face_test/data/experiments/COFW/__init__.py
face_test/data/experiments/COFW/pip_32_16_60_r18_l2_l1_10_1_nb10.py
face_test/data/experiments/WFLW/__init__.py
face_test/data/experiments/WFLW/pip_32_16_60_mv3_large_l2_l1_10_1_nb10.py
face_test/data/experiments/WFLW/pip_32_16_60_mv3_small_l2_l1_10_1_nb10.py
face_test/data/experiments/WFLW/pip_32_16_60_r18_l2_l1_10_1_nb10.py
face_test/data/experiments/data_300W/__init__.py
face_test/data/experiments/data_300W/pip_32_16_60_r18_l2_l1_10_1_nb10.py
face_test/eval/__init__.py
face_test/eval/commands/__init__.py
face_test/eval/commands/eval_ijbc.py
face_test/eval/commands/eval_megaface.py
face_test/eval/commands/eval_verification.py
face_test/eval/commands/run.py
face_test/eval/ijbc/__init__.py
face_test/eval/ijbc/eval_ijbc.py
face_test/eval/ijbc/ijbc_run.py
face_test/eval/megaface/__init__.py
face_test/eval/megaface/gen_features_lst.py
face_test/eval/megaface/interpolation.py
face_test/eval/megaface/megaface_results.py
face_test/eval/megaface/megaface_run.py
face_test/eval/megaface/remove_noises.py
face_test/eval/megaface/run_experiment.py
face_test/eval/verification/__init__.py
face_test/eval/verification/verification.py
face_test/eval/verification/eval_util/__init__.py
face_test/eval/verification/eval_util/verification.py
face_test/eval/verification/eval_util/verification_g.py
face_test/eval/verification/eval_util/verification_m.py
face_test/face/__init__.py
face_test/face/common.py
face_test/face/get_result.py
face_test/model_zoo/__init__.py
face_test/model_zoo/get_models.py
face_test/model_zoo/backbones/__init__.py
face_package-1.1.27.dist-info/METADATA
face_package-1.1.27.dist-info/WHEEL
face_package-1.1.27.dist-info/entry_points.txt
face_package-1.1.27.dist-info/top_level.txt
face_package-1.1.27.dist-info/RECORD
