Metadata-Version: 2.1
Name: face-package
Version: 1.1.27
Summary: Test Face model
Author: minsuny
Author-email: minsun.y@nsensecorp.com
Requires-Python: >=3
Requires-Dist: pickle5
Requires-Dist: mxnet
Requires-Dist: menpo
Requires-Dist: onnxruntime
Requires-Dist: onnxruntime-gpu
Requires-Dist: openvino (==2022.2.0)
Requires-Dist: scikit-image
Requires-Dist: scikit-learn
Requires-Dist: pillow
Requires-Dist: opencv-python
